PyQt5/Qt.abi3.so
PyQt5/Qt5/qsci/api/python/PyQt5.api
PyQt5/QtBluetooth.abi3.so
PyQt5/QtBluetooth.pyi
PyQt5/QtCore.abi3.so
PyQt5/QtCore.pyi
PyQt5/QtDBus.abi3.so
PyQt5/QtDBus.pyi
PyQt5/QtDesigner.abi3.so
PyQt5/QtDesigner.pyi
PyQt5/QtGui.abi3.so
PyQt5/QtGui.pyi
PyQt5/QtHelp.abi3.so
PyQt5/QtHelp.pyi
PyQt5/QtLocation.abi3.so
PyQt5/QtLocation.pyi
PyQt5/QtMultimedia.abi3.so
PyQt5/QtMultimedia.pyi
PyQt5/QtMultimediaWidgets.abi3.so
PyQt5/QtMultimediaWidgets.pyi
PyQt5/QtNetwork.abi3.so
PyQt5/QtNetwork.pyi
PyQt5/QtNfc.abi3.so
PyQt5/QtNfc.pyi
PyQt5/QtOpenGL.abi3.so
PyQt5/QtOpenGL.pyi
PyQt5/QtPositioning.abi3.so
PyQt5/QtPositioning.pyi
PyQt5/QtPrintSupport.abi3.so
PyQt5/QtPrintSupport.pyi
PyQt5/QtQml.abi3.so
PyQt5/QtQml.pyi
PyQt5/QtQuick.abi3.so
PyQt5/QtQuick.pyi
PyQt5/QtQuick3D.abi3.so
PyQt5/QtQuick3D.pyi
PyQt5/QtQuickWidgets.abi3.so
PyQt5/QtQuickWidgets.pyi
PyQt5/QtRemoteObjects.abi3.so
PyQt5/QtRemoteObjects.pyi
PyQt5/QtSensors.abi3.so
PyQt5/QtSensors.pyi
PyQt5/QtSerialPort.abi3.so
PyQt5/QtSerialPort.pyi
PyQt5/QtSql.abi3.so
PyQt5/QtSql.pyi
PyQt5/QtSvg.abi3.so
PyQt5/QtSvg.pyi
PyQt5/QtTest.abi3.so
PyQt5/QtTest.pyi
PyQt5/QtTextToSpeech.abi3.so
PyQt5/QtTextToSpeech.pyi
PyQt5/QtWebChannel.abi3.so
PyQt5/QtWebChannel.pyi
PyQt5/QtWebSockets.abi3.so
PyQt5/QtWebSockets.pyi
PyQt5/QtWidgets.abi3.so
PyQt5/QtWidgets.pyi
PyQt5/QtX11Extras.abi3.so
PyQt5/QtX11Extras.pyi
PyQt5/QtXml.abi3.so
PyQt5/QtXml.pyi
PyQt5/QtXmlPatterns.abi3.so
PyQt5/QtXmlPatterns.pyi
PyQt5/_QOpenGLFunctions_2_0.abi3.so
PyQt5/_QOpenGLFunctions_2_1.abi3.so
PyQt5/_QOpenGLFunctions_4_1_Core.abi3.so
PyQt5/__init__.py
PyQt5/bindings/QtBluetooth/QtBluetooth.toml
PyQt5/bindings/QtBluetooth/QtBluetoothmod.sip
PyQt5/bindings/QtBluetooth/qbluetooth.sip
PyQt5/bindings/QtBluetooth/qbluetoothaddress.sip
PyQt5/bindings/QtBluetooth/qbluetoothdevicediscoveryagent.sip
PyQt5/bindings/QtBluetooth/qbluetoothdeviceinfo.sip
PyQt5/bindings/QtBluetooth/qbluetoothhostinfo.sip
PyQt5/bindings/QtBluetooth/qbluetoothlocaldevice.sip
PyQt5-5.15.8.dist-info/entry_points.txt
PyQt5-5.15.8.dist-info/WHEEL
PyQt5-5.15.8.dist-info/METADATA
PyQt5-5.15.8.dist-info/RECORD
