Metadata-Version: 2.1
Name: PyQt5
Version: 5.15.8
Requires-Python: >=3.7
Summary: Python bindings for the Qt cross platform application toolkit
Home-Page: https://www.riverbankcomputing.com/software/pyqt/
Author: Riverbank Computing Limited
Author-Email: info@riverbankcomputing.com
License: GPL v3
Requires-Dist: PyQt5-sip (>=12.11, <13)
Requires-Dist: PyQt5-Qt5 (>=5.15.2)
